cloudsat
